__init__.py
build/__init__.py
build/lib/__init__.py
build/lib/build/__init__.py
build/lib/build/lib/__init__.py
build/lib/build/lib/build/__init__.py
build/lib/build/lib/build/lib/__init__.py
build/lib/build/lib/build/lib/build/__init__.py
build/lib/build/lib/build/lib/build/lib/__init__.py
build/lib/build/lib/build/lib/build/lib/google/__init__.py
build/lib/build/lib/build/lib/build/lib/google/api/__init__.py
build/lib/build/lib/build/lib/build/lib/google/api/annotations_grpc.py
build/lib/build/lib/build/lib/build/lib/google/api/annotations_pb2.py
build/lib/build/lib/build/lib/build/lib/google/api/http_grpc.py
build/lib/build/lib/build/lib/build/lib/google/api/http_pb2.py
build/lib/build/lib/build/lib/build/lib/google/protobuf/__init__.py
build/lib/build/lib/build/lib/build/lib/google/protobuf/timestamp_grpc.py
build/lib/build/lib/build/lib/build/lib/google/protobuf/timestamp_pb2.py
build/lib/build/lib/build/lib/build/lib/ozonmp/__init__.py
build/lib/build/lib/build/lib/build/lib/ozonmp/act_correction_api/__init__.py
build/lib/build/lib/build/lib/build/lib/ozonmp/act_correction_api/v1/__init__.py
build/lib/build/lib/build/lib/build/lib/ozonmp/act_correction_api/v1/act_correction_api_grpc.py
build/lib/build/lib/build/lib/build/lib/ozonmp/act_correction_api/v1/act_correction_api_pb2.py
build/lib/build/lib/build/lib/build/lib/validate/__init__.py
build/lib/build/lib/build/lib/build/lib/validate/validate_grpc.py
build/lib/build/lib/build/lib/build/lib/validate/validate_pb2.py
build/lib/build/lib/build/lib/dist/__init__.py
build/lib/build/lib/build/lib/google/__init__.py
build/lib/build/lib/build/lib/google/api/__init__.py
build/lib/build/lib/build/lib/google/api/annotations_grpc.py
build/lib/build/lib/build/lib/google/api/annotations_pb2.py
build/lib/build/lib/build/lib/google/api/http_grpc.py
build/lib/build/lib/build/lib/google/api/http_pb2.py
build/lib/build/lib/build/lib/google/protobuf/__init__.py
build/lib/build/lib/build/lib/google/protobuf/timestamp_grpc.py
grpc_act_correction_api-1.0.0.dist-info/LICENSE
grpc_act_correction_api-1.0.0.dist-info/METADATA
grpc_act_correction_api-1.0.0.dist-info/WHEEL
grpc_act_correction_api-1.0.0.dist-info/__init__.py
grpc_act_correction_api-1.0.0.dist-info/top_level.txt
grpc_act_correction_api-1.0.0.dist-info/RECORD
