Metadata-Version: 2.1
Name: grpc-act-correction-api
Version: 1.0.0
Summary: GRPC python client for act-correction-api
Home-page: https://github.com/ozonmp/act-correction-api
Author: lgalkina
Author-email: liudmila.galkina@gmail.com
License: UNKNOWN
Platform: UNKNOWN
Requires-Python: >=3.5
